[  {    "type": "POST",    "url": "/api/v1/sync-book",    "title": "Add Rating",    "name": "Add_Rating",    "group": "SyncBook",    "description": "<p>Add new rating for a book</p>",    "parameter": {      "examples": [        {          "title": "POST Request-Example:",          "content": "{\n  \"rating\": \"4.5\",\n}",          "type": "json"        }      ]    },    "success": {      "fields": {        "Success 200": [          {            "group": "Success 200",            "type": "Object",            "optional": false,            "field": "response",            "description": "<p>JSON Object</p>"          }        ]      },      "examples": [        {          "title": "Success-Response:",          "content": "{\n  \"book\": {\n    \"ratings\": \"4.63\",\n    \"description\": \"In one devastating night, violin prodigy Etta Spencer loses \",\n    \"imageUrl\": \"/image/path/passenger.jpg\",\n    \"datePublished\": \"Tue Dec 06 2016\",\n    \"author\": \"Alexandra Bracken\",\n    \"title\": \"Passenger\",\n    \"_id\": \"58e44447354ee62f72f7322d\"\n  }\n}",          "type": "json"        }      ]    },    "error": {      "fields": {        "Error 4xx": [          {            "group": "Error 4xx",            "type": "Object",            "optional": false,            "field": "error",            "description": "<p>JSON Object with error message</p>"          }        ]      },      "examples": [        {          "title": "Error-Response:",          "content": "{\n \"error\": \"message\"\n}",          "type": "json"        }      ]    },    "version": "0.0.0",    "filename": "./routes/syncbook.js",    "groupTitle": "SyncBook"  },  {    "type": "GET",    "url": "/api/v1/sync-book/:id",    "title": "Book Details",    "name": "GetBook",    "group": "SyncBook",    "parameter": {      "fields": {        "Parameter": [          {            "group": "Parameter",            "type": "string",            "optional": false,            "field": "id",            "description": "<p>Assessment ID.</p>"          }        ]      }    },    "description": "<p>Get book details object using id</p>",    "success": {      "fields": {        "Success 200": [          {            "group": "Success 200",            "type": "Object",            "optional": false,            "field": "response",            "description": ""          }        ]      },      "examples": [        {          "title": "Success-Response:",          "content": "{\n  \"book\": {\n    \"ratings\": \"4.63\",\n    \"description\": \"In one devastating night, violin prodigy Etta Spencer loses \",\n    \"imageUrl\": \"/image/path/passenger.jpg\",\n    \"datePublished\": \"Tue Dec 06 2016\",\n    \"author\": \"Alexandra Bracken\",\n    \"title\": \"Passenger\",\n    \"_id\": \"58e44447354ee62f72f7322d\"\n  }\n}",          "type": "json"        }      ]    },    "error": {      "fields": {        "Error 4xx": [          {            "group": "Error 4xx",            "type": "Object",            "optional": false,            "field": "response",            "description": ""          }        ]      },      "examples": [        {          "title": "Error-Response:",          "content": "{\n \"error\": \"message\"\n}",          "type": "json"        }      ]    },    "version": "0.0.0",    "filename": "./routes/syncbook.js",    "groupTitle": "SyncBook"  },  {    "type": "GET",    "url": "/api/v1/sync-book",    "title": "List Books",    "name": "GetBooks",    "group": "SyncBook",    "description": "<p>Get All books</p>",    "success": {      "fields": {        "Success 200": [          {            "group": "Success 200",            "type": "Object",            "optional": false,            "field": "response",            "description": ""          }        ]      },      "examples": [        {          "title": "Success-Response:",          "content": "{\n  \"books\": [\n    {\n      \"ratings\": \"4.30\",\n      \"imageUrl\": \"/image/path/50shadesgrey.jpg\",\n      \"datePublished\": \"Tue Apr 03 2012\",\n      \"author\": \"E. L. James\",\n      \"title\": \"Fifty Shades of Grey\",\n      \"_id\": \"58e44447354ee62f72f7321d\"\n    },\n    {\n      \"ratings\": \"4.10\",\n      \"imageUrl\": \"/image/path/hunger_games1.jpg\",\n      \"datePublished\": \"Sat Jul 03 2010\",\n      \"author\": \"Suzanne Collins\",\n      \"title\": \"The Hunger Games (Book 1)\",\n      \"_id\": \"58e44447354ee62f72f7321e\"\n    }\n  ]\n}",          "type": "json"        }      ]    },    "error": {      "fields": {        "Error 4xx": [          {            "group": "Error 4xx",            "type": "Object",            "optional": false,            "field": "response",            "description": ""          }        ]      },      "examples": [        {          "title": "Error-Response:",          "content": "{\n \"error\": \"message\"\n}",          "type": "json"        }      ]    },    "version": "0.0.0",    "filename": "./routes/syncbook.js",    "groupTitle": "SyncBook"  },  {    "success": {      "fields": {        "Success 200": [          {            "group": "Success 200",            "optional": false,            "field": "varname1",            "description": "<p>No type.</p>"          },          {            "group": "Success 200",            "type": "String",            "optional": false,            "field": "varname2",            "description": "<p>With type.</p>"          }        ]      }    },    "type": "",    "url": "",    "version": "0.0.0",    "filename": "./doc/main.js",    "group": "_Users_chukwuma_Documents_work_syn_service_api_doc_main_js",    "groupTitle": "_Users_chukwuma_Documents_work_syn_service_api_doc_main_js",    "name": ""  }]
